bob/__init__.py
bob/pad/__init__.py
bob/pad/base/__init__.py
bob/pad/base/error_utils.py
bob/pad/base/config/__init__.py
bob/pad/base/database/__init__.py
bob/pad/base/database/csv_dataset.py
bob/pad/base/pipelines/__init__.py
bob/pad/base/pipelines/abstract_classes.py
bob/pad/base/script/__init__.py
bob/pad/base/script/cross.py
bob/pad/base/script/finalize_scores.py
bob/pad/base/script/pad.py
bob/pad/base/script/pad_commands.py
bob/pad/base/script/pad_figure.py
bob/pad/base/script/run_pipeline.py
bob.pad.base-6.0.1.dist-info/COPYING
bob.pad.base-6.0.1.dist-info/METADATA
bob.pad.base-6.0.1.dist-info/WHEEL
bob.pad.base-6.0.1.dist-info/entry_points.txt
bob.pad.base-6.0.1.dist-info/top_level.txt
bob.pad.base-6.0.1.dist-info/RECORD
