Metadata-Version: 2.1
Name: bob.pad.base
Version: 6.0.1
Summary: A framework for executing the chain of presentation attack detection (PAD) experiments
Author: Pavel Korshunov
Author-email: pavel.korshunov@idiap.ch
License: GPLv3 License
Project-URL: documentation, https://www.idiap.ch/software/bob/docs/bob/bob.pad.base/v6.0.1/sphinx/
Project-URL: homepage, https://pypi.org/project/bob.pad.base/
Project-URL: repository, https://gitlab.idiap.ch/bob/bob.pad.base
Project-URL: changelog, https://gitlab.idiap.ch/bob/bob.pad.base/-/releases
Keywords: PAD framework,grid support,pipeline organization
Classifier: Framework :: Bob
Classifier: Development Status :: 3 - Alpha
Classifier: Intended Audience :: Developers
Classifier: License :: OSI Approved :: GNU General Public License v3 (GPLv3)
Classifier: Natural Language :: English
Classifier: Programming Language :: Python
Classifier: Topic :: Scientific/Engineering :: Artificial Intelligence
Requires-Python: >=3.9
License-File: COPYING
Requires-Dist: bob ==12.1.1
Requires-Dist: bob.io.base ==5.1.1
Requires-Dist: bob.measure ==6.1.1
Requires-Dist: bob.pipelines ==4.0.1
Requires-Dist: bob.bio.base ==8.1.1
Requires-Dist: clapper ~=1.0
Requires-Dist: click ~=8.1
Requires-Dist: click-plugins ~=1.1
Requires-Dist: dask ==2024.5.2
Requires-Dist: matplotlib ~=3.8
Requires-Dist: numpy ~=1.26
Requires-Dist: scikit-learn ~=1.4
Requires-Dist: scipy ~=1.10
Requires-Dist: sqlalchemy ~=2.0
Requires-Dist: tabulate ~=0.9
Provides-Extra: doc
Requires-Dist: sphinx ; extra == 'doc'
Requires-Dist: sphinx-rtd-theme ; extra == 'doc'
Requires-Dist: sphinx-autodoc-typehints ; extra == 'doc'
Requires-Dist: auto-intersphinx ; extra == 'doc'
Requires-Dist: sphinxcontrib-programoutput ; extra == 'doc'
Requires-Dist: matplotlib ; extra == 'doc'
Provides-Extra: qa
Requires-Dist: pre-commit ; extra == 'qa'
Provides-Extra: test
Requires-Dist: pytest ; extra == 'test'
Requires-Dist: pytest-cov ; extra == 'test'
Requires-Dist: coverage ; extra == 'test'
